pytropic/__init__.py
pytropic/pytropic.py
pytropic-1.1.1.dist-info/LICENSE
pytropic-1.1.1.dist-info/WHEEL
pytropic-1.1.1.dist-info/METADATA
pytropic-1.1.1.dist-info/RECORD
