Metadata-Version: 2.1
Name: pytropic
Version: 1.1.1
Summary: Train and predict string entropy based on character n-grams
License: MIT
Author: Will Fitzgerald
Author-email: 37049+willf@users.noreply.github.com
Requires-Python: >=3.10,<4.0
Classifier: License :: OSI Approved :: MIT License
Classifier: Programming Language :: Python :: 3
Classifier: Programming Language :: Python :: 3.10
Classifier: Programming Language :: Python :: 3.11
